chain_index/__init__.py
chain_index/constants.py
chain_index/core.py
chain_index/exceptions.py
chain_index/protocols.py
chain_index/data/chains.json
chain_index/data/common_tokens.json
chain_index-0.3.0.dist-info/LICENSE
chain_index-0.3.0.dist-info/METADATA
chain_index-0.3.0.dist-info/WHEEL
chain_index-0.3.0.dist-info/top_level.txt
chain_index-0.3.0.dist-info/RECORD
