Metadata-Version: 2.1
Name: chain-index
Version: 0.3.0
Summary: A Python library for managing and organizing AI language model chains
Author-email: gmatrix <gmatrixuniverse@gmail.com>
License: MIT License
Project-URL: Homepage, https://github.com/gmatrixuniverse/chain_index
Keywords: web3,ethereum,blockchain,evm
Classifier: License :: OSI Approved :: MIT License
Classifier: Programming Language :: Python
Classifier: Programming Language :: Python :: 3
Requires-Python: >=3.7
License-File: LICENSE
Requires-Dist: pydantic>=1.8.0
Requires-Dist: typing-extensions>=3.7.4
Requires-Dist: eth-abi>=4.0.0
Requires-Dist: eth-utils>=2.0.0
Provides-Extra: dev
Requires-Dist: pytest; extra == "dev"
